evan/__init__.py
evan/sung.py
examples/__init__.py
evansung-1.5.dist-info/LICENSE
evansung-1.5.dist-info/METADATA
evansung-1.5.dist-info/WHEEL
evansung-1.5.dist-info/top_level.txt
evansung-1.5.dist-info/RECORD
