Metadata-Version: 2.1
Name: evansung
Version: 1.5
Summary: evansung yyds
Home-page: UNKNOWN
Author: evansung
Author-email: evansung@outlook.com
License: UNKNOWN
Platform: UNKNOWN
Classifier: Programming Language :: Python :: 3
Classifier: License :: OSI Approved :: MIT License
Classifier: Operating System :: OS Independent
Requires-Python: >=3
Requires-Dist: pillow
